lance_namespace_urllib3_client/__init__.py
lance_namespace_urllib3_client/api_client.py
lance_namespace_urllib3_client/api_response.py
lance_namespace_urllib3_client/configuration.py
lance_namespace_urllib3_client/exceptions.py
lance_namespace_urllib3_client/py.typed
lance_namespace_urllib3_client/rest.py
lance_namespace_urllib3_client/api/__init__.py
lance_namespace_urllib3_client/api/data_api.py
lance_namespace_urllib3_client/api/index_api.py
lance_namespace_urllib3_client/api/metadata_api.py
lance_namespace_urllib3_client/api/namespace_api.py
lance_namespace_urllib3_client/api/table_api.py
lance_namespace_urllib3_client/api/tag_api.py
lance_namespace_urllib3_client/api/transaction_api.py
lance_namespace_urllib3_client/models/__init__.py
lance_namespace_urllib3_client/models/add_virtual_column_entry.py
lance_namespace_urllib3_client/models/alter_columns_entry.py
lance_namespace_urllib3_client/models/alter_table_add_columns_request.py
lance_namespace_urllib3_client/models/alter_table_add_columns_response.py
lance_namespace_urllib3_client/models/alter_table_alter_columns_request.py
lance_namespace_urllib3_client/models/alter_table_alter_columns_response.py
lance_namespace_urllib3_client/models/alter_table_drop_columns_request.py
lance_namespace_urllib3_client/models/alter_table_drop_columns_response.py
lance_namespace_urllib3_client/models/alter_transaction_action.py
lance_namespace_urllib3_client/models/alter_transaction_request.py
lance_namespace_urllib3_client/models/alter_transaction_response.py
lance_namespace_urllib3_client/models/alter_transaction_set_property.py
lance_namespace_urllib3_client/models/alter_transaction_set_status.py
lance_namespace_urllib3_client/models/alter_transaction_unset_property.py
lance_namespace_urllib3_client/models/alter_virtual_column_entry.py
lance_namespace_urllib3_client/models/analyze_table_query_plan_request.py
lance_namespace_urllib3_client/models/analyze_table_query_plan_response.py
lance_namespace_urllib3_client-0.4.4.dist-info/METADATA
lance_namespace_urllib3_client-0.4.4.dist-info/WHEEL
lance_namespace_urllib3_client-0.4.4.dist-info/RECORD
