Metadata-Version: 2.4
Name: lance-namespace-urllib3-client
Version: 0.4.4
Summary: Lance Namespace Specification
Project-URL: Repository, https://github.com/lance-format/lance-namespace
Author-email: Lance Devs <dev@lance.org>
License: Apache-2.0
Keywords: Lance Namespace Specification,OpenAPI,OpenAPI-Generator
Requires-Python: >=3.8
Requires-Dist: pydantic>=2
Requires-Dist: python-dateutil>=2.8.2
Requires-Dist: typing-extensions>=4.7.1
Requires-Dist: urllib3<3.0.0,>=1.25.3
